{
  "alpha_kwh_per_tonne": 109.0,
  "total_demand_tonnes": 28000000.0,
  "total_demand_Mt": 28.0,
  "rated_capacity_t_h": 4450.0,
  "rated_capacity_Mt_yr": 38.982,
  "ramp_limit_frac": 0.05,
  "ramp_limit_t_h": 222.5,
  "s_max_days": 5,
  "s_max_tonnes": 534000.0,
  "min_load_frac": 0.6,
  "min_load_t_h": 2670.0,
  "thermal_kwh_per_tonne": 780,
  "avg_heat_value_gj_t": 2.81,
  "process_co2_kg_t": 520,
  "energy_co2_kg_t": 160,
  "source": "VDZ Environmental Data 2023, hard-coded values",
  "reference": "https://www.vdz-online.de/en/knowledge-base/publications/environmental-data-of-the-german-cement-industry-2023",
  "extraction_method": "hard_coded",
  "units": {
    "alpha_kwh_per_tonne": "kWh_el/tonne cement",
    "total_demand_tonnes": "tonnes/year",
    "rated_capacity_t_h": "tonnes/hour",
    "ramp_limit_frac": "fraction of rated capacity per hour",
    "ramp_limit_t_h": "tonnes/hour/hour",
    "s_max_days": "days",
    "s_max_tonnes": "tonnes",
    "min_load_frac": "fraction of rated capacity",
    "min_load_t_h": "tonnes/hour",
    "thermal_kwh_per_tonne": "kWh_th/tonne clinker",
    "avg_heat_value_gj_t": "GJ/tonne clinker",
    "process_co2_kg_t": "kg CO2/tonne clinker (calcination only)",
    "energy_co2_kg_t": "kg CO2/tonne clinker (fuel combustion)"
  },
  "annual_elec_demand_GWh": 3052.0,
  "annual_elec_demand_TWh": 3.052,
  "utilisation_pct": 71.8
}